Metadata-Version: 2.1
Name: ace-magnetometer
Version: 0.9.0
Summary: Load and Plot ACE satellite magnetometer data
Home-page: https://github.com/scivision/ace_magnetometer
Author: Michael Hirsch, Ph.D.
License: UNKNOWN
Keywords: IMF,magnetic field,geospace
Platform: UNKNOWN
Classifier: Development Status :: 5 - Production/Stable
Classifier: Environment :: Console
Classifier: Intended Audience :: Science/Research
Classifier: Operating System :: OS Independent
Classifier: Programming Language :: Python :: 3.6
Classifier: Programming Language :: Python :: 3.7
Classifier: Topic :: Scientific/Engineering :: Atmospheric Science
Requires-Python: >= 3.6
Provides-Extra: tests
Provides-Extra: plot
